earth2studio/__init__.py
earth2studio/run.py
earth2studio/data/__init__.py
earth2studio/data/ace2.py
earth2studio/data/arco.py
earth2studio/data/base.py
earth2studio/data/cbottle.py
earth2studio/data/cds.py
earth2studio/data/cmip6.py
earth2studio/data/const.py
earth2studio/data/ecmwf.py
earth2studio/data/gefs.py
earth2studio/data/gfs.py
earth2studio/data/goes.py
earth2studio/data/hrrr.py
earth2studio/data/isd.py
earth2studio/data/jpss.py
earth2studio/data/mrms.py
earth2studio/data/msc_config.yaml
earth2studio/data/ncar.py
earth2studio/data/planetary_computer.py
earth2studio/data/rand.py
earth2studio/data/rx.py
earth2studio/data/time_window.py
earth2studio/data/utils.py
earth2studio/data/wb2.py
earth2studio/data/xr.py
earth2studio/io/__init__.py
earth2studio/io/async_zarr.py
earth2studio/io/base.py
earth2studio/io/kv.py
earth2studio/io/netcdf4.py
earth2studio/io/xarray.py
earth2studio/io/zarr.py
earth2studio/lexicon/__init__.py
earth2studio/lexicon/ace.py
earth2studio/lexicon/arco.py
earth2studio/lexicon/base.py
earth2studio/lexicon/cbottle.py
earth2studio/lexicon/cds.py
earth2studio/lexicon/cmip6.py
earth2studio/lexicon/ecmwf.py
earth2studio/lexicon/gefs.py
earth2studio/lexicon/gfs.py
earth2studio/lexicon/goes.py
earth2studio/lexicon/hrrr.py
earth2studio/lexicon/isd.py
earth2studio/lexicon/jpss.py
earth2studio/lexicon/mrms.py
earth2studio/lexicon/ncar.py
earth2studio/lexicon/planetary_computer.py
earth2studio/lexicon/wb2.py
earth2studio/models/batch.py
earth2studio/models/utils.py
earth2studio/models/auto/__init__.py
earth2studio/models/auto/mixin.py
earth2studio/models/auto/ngc.py
earth2studio/models/auto/package.py
earth2studio/models/dx/__init__.py
earth2studio/models/dx/base.py
earth2studio/models/dx/cbottle_infill.py
earth2studio/models/dx/cbottle_sr.py
earth2studio/models/dx/cbottle_tc.py
earth2studio/models/dx/climatenet.py
earth2studio/models/dx/corrdiff.py
earth2studio/models/dx/corrdiff_cmip6.py
earth2studio/models/dx/derived.py
earth2studio-0.12.1.dist-info/METADATA
earth2studio-0.12.1.dist-info/WHEEL
earth2studio-0.12.1.dist-info/licenses/LICENSE
earth2studio-0.12.1.dist-info/RECORD
