Metadata-Version: 2.4
Name: earth2studio
Version: 0.12.1
Summary: Open-source deep-learning framework for exploring, building and deploying AI weather/climate workflows.
Project-URL: Homepage, https://github.com/NVIDIA/earth2studio
Project-URL: Documentation, https://nvidia.github.io/earth2studio
Project-URL: Issues, https://github.com/NVIDIA/earth2studio/issues
Project-URL: Changelog, https://github.com/NVIDIA/earth2studio/blob/main/CHANGELOG.md
Author: NVIDIA PhysicsNeMo Team
License-Expression: Apache-2.0
License-File: LICENSE
Classifier: Environment :: GPU
Classifier: Intended Audience :: Science/Research
Classifier: License :: OSI Approved :: Apache Software License
Classifier: Operating System :: OS Independent
Classifier: Programming Language :: Python
Classifier: Programming Language :: Python :: 3
Classifier: Programming Language :: Python :: 3 :: Only
Classifier: Programming Language :: Python :: 3.11
Classifier: Programming Language :: Python :: 3.12
Classifier: Programming Language :: Python :: 3.13
Classifier: Topic :: Scientific/Engineering :: Artificial Intelligence
Classifier: Typing :: Typed
Requires-Python: >=3.11
Requires-Dist: cftime
Requires-Dist: fsspec>=2024.2.0
Requires-Dist: gcsfs
Requires-Dist: h5netcdf>=1.0.0
Requires-Dist: h5py>=3.2.0
Requires-Dist: huggingface-hub>=0.27.0
Requires-Dist: loguru
Requires-Dist: nest-asyncio
Requires-Dist: netcdf4<1.7.3,>=1.6.4
Requires-Dist: pandas<3.0
Requires-Dist: pygrib
Requires-Dist: python-dotenv
Requires-Dist: rich
Requires-Dist: s3fs>=2023.5.0
Requires-Dist: torch>=2.5.0
Requires-Dist: tqdm>=4.65.0
Requires-Dist: xarray[parallel]>=2023.1.0
Requires-Dist: zarr>=3.1.0
Provides-Extra: ace2
Requires-Dist: fme; extra == 'ace2'
Requires-Dist: h5py<=3.14.0; extra == 'ace2'
Requires-Dist: pandas>=2.3.2; extra == 'ace2'
Requires-Dist: scipy>=1.15.2; extra == 'ace2'
Provides-Extra: aifs
Requires-Dist: anemoi-models==0.5.1; extra == 'aifs'
Requires-Dist: earthkit-regrid==0.4.0; extra == 'aifs'
Requires-Dist: ecmwf-opendata>=0.3.3; extra == 'aifs'
Requires-Dist: flash-attn; extra == 'aifs'
Provides-Extra: aifsens
Requires-Dist: anemoi-models==0.5.1; extra == 'aifsens'
Requires-Dist: earthkit-regrid==0.4.0; extra == 'aifsens'
Requires-Dist: ecmwf-opendata>=0.3.3; extra == 'aifsens'
Requires-Dist: flash-attn; extra == 'aifsens'
Provides-Extra: all
Requires-Dist: anemoi-models==0.5.1; extra == 'all'
Requires-Dist: cbottle; (python_full_version >= '3.12') and extra == 'all'
Requires-Dist: cdsapi>=0.7.5; extra == 'all'
Requires-Dist: cfgrib>=0.9.10.3; extra == 'all'
Requires-Dist: cucim-cu12>=25.4.0; extra == 'all'
Requires-Dist: dm-haiku>=0.0.14; extra == 'all'
Requires-Dist: dm-tree>=0.1.9; extra == 'all'
Requires-Dist: earth2grid; extra == 'all'
Requires-Dist: earthkit-regrid==0.4.0; extra == 'all'
Requires-Dist: eccodes>=2.38.0; extra == 'all'
Requires-Dist: ecmwf-opendata>=0.3.3; extra == 'all'
Requires-Dist: einops; extra == 'all'
Requires-Dist: einops>=0.8.1; extra == 'all'
Requires-Dist: flash-attn; extra == 'all'
Requires-Dist: flax>=0.10.6; extra == 'all'
Requires-Dist: fme; extra == 'all'
Requires-Dist: globus-sdk<4.0.0; extra == 'all'
Requires-Dist: graphcast; extra == 'all'
Requires-Dist: h5py<=3.14.0; extra == 'all'
Requires-Dist: httpx==0.28.1; extra == 'all'
Requires-Dist: hydra-core>=1.3.2; extra == 'all'
Requires-Dist: importlib-metadata; extra == 'all'
Requires-Dist: intake-esgf>=2025.9.26; extra == 'all'
Requires-Dist: jax[cuda12]>=0.4.26; extra == 'all'
Requires-Dist: makani; extra == 'all'
Requires-Dist: microsoft-aurora>=1.6.0; extra == 'all'
Requires-Dist: moviepy; extra == 'all'
Requires-Dist: multi-storage-client[boto3,fsspec,google-cloud-storage]>=0.33.0; extra == 'all'
Requires-Dist: natten; extra == 'all'
Requires-Dist: nvidia-physicsnemo<2.0,>=1.0.1; extra == 'all'
Requires-Dist: nvidia-physicsnemo<2.0,>=1.2.0; extra == 'all'
Requires-Dist: nvidia-physicsnemo<2.0,>=1.3.0; extra == 'all'
Requires-Dist: nvidia-physicsnemo==1.3.0; extra == 'all'
Requires-Dist: nvtx>=0.2.11; extra == 'all'
Requires-Dist: omegaconf>=2.3.0; extra == 'all'
Requires-Dist: onnx; extra == 'all'
Requires-Dist: onnxruntime-gpu>=1.21.0; extra == 'all'
Requires-Dist: onnxscript; extra == 'all'
Requires-Dist: pandas<3.0; extra == 'all'
Requires-Dist: pandas>=2.3.2; extra == 'all'
Requires-Dist: planetary-computer>=0.5.0; extra == 'all'
Requires-Dist: pynvml>=12.0.0; extra == 'all'
Requires-Dist: pyproj>=3.7.1; extra == 'all'
Requires-Dist: pystac-client>=0.9.0; extra == 'all'
Requires-Dist: pytz; extra == 'all'
Requires-Dist: rasterio>=1.3.9; extra == 'all'
Requires-Dist: rioxarray>=0.15.5; extra == 'all'
Requires-Dist: ruamel-yaml>=0.18.10; extra == 'all'
Requires-Dist: ruamel-yaml>=0.18.14; extra == 'all'
Requires-Dist: scikit-image>=0.25.2; extra == 'all'
Requires-Dist: scipy>=1.10.0; extra == 'all'
Requires-Dist: scipy>=1.15.2; extra == 'all'
Requires-Dist: timm; extra == 'all'
Requires-Dist: torch-harmonics; extra == 'all'
Requires-Dist: torch-harmonics>=0.7.4; extra == 'all'
Requires-Dist: torch-harmonics>=0.8.0; extra == 'all'
Provides-Extra: atlas
Requires-Dist: einops; extra == 'atlas'
Requires-Dist: natten; extra == 'atlas'
Requires-Dist: nvidia-physicsnemo<2.0,>=1.3.0; extra == 'atlas'
Requires-Dist: pytz; extra == 'atlas'
Requires-Dist: timm; extra == 'atlas'
Requires-Dist: torch-harmonics; extra == 'atlas'
Provides-Extra: aurora
Requires-Dist: microsoft-aurora>=1.6.0; extra == 'aurora'
Provides-Extra: cbottle
Requires-Dist: cbottle; (python_full_version >= '3.12') and extra == 'cbottle'
Requires-Dist: earth2grid; extra == 'cbottle'
Provides-Extra: climatenet
Provides-Extra: corrdiff
Requires-Dist: einops>=0.8.1; extra == 'corrdiff'
Requires-Dist: nvidia-physicsnemo<2.0,>=1.2.0; extra == 'corrdiff'
Requires-Dist: nvtx>=0.2.11; extra == 'corrdiff'
Requires-Dist: pytz; extra == 'corrdiff'
Requires-Dist: scipy>=1.15.2; extra == 'corrdiff'
Provides-Extra: cyclone
Requires-Dist: cucim-cu12>=25.4.0; extra == 'cyclone'
Requires-Dist: scikit-image>=0.25.2; extra == 'cyclone'
Provides-Extra: data
Requires-Dist: cdsapi>=0.7.5; extra == 'data'
Requires-Dist: cfgrib>=0.9.10.3; extra == 'data'
Requires-Dist: eccodes>=2.38.0; extra == 'data'
Requires-Dist: ecmwf-opendata>=0.3.3; extra == 'data'
Requires-Dist: globus-sdk<4.0.0; extra == 'data'
Requires-Dist: httpx==0.28.1; extra == 'data'
Requires-Dist: intake-esgf>=2025.9.26; extra == 'data'
Requires-Dist: multi-storage-client[boto3,fsspec,google-cloud-storage]>=0.33.0; extra == 'data'
Requires-Dist: pandas<3.0; extra == 'data'
Requires-Dist: planetary-computer>=0.5.0; extra == 'data'
Requires-Dist: pyproj>=3.7.1; extra == 'data'
Requires-Dist: pystac-client>=0.9.0; extra == 'data'
Requires-Dist: rasterio>=1.3.9; extra == 'data'
Requires-Dist: rioxarray>=0.15.5; extra == 'data'
Requires-Dist: scipy>=1.15.2; extra == 'data'
Provides-Extra: derived
Provides-Extra: dlesym
Requires-Dist: earth2grid; extra == 'dlesym'
Requires-Dist: hydra-core>=1.3.2; extra == 'dlesym'
Requires-Dist: nvidia-physicsnemo<2.0,>=1.0.1; extra == 'dlesym'
Requires-Dist: omegaconf>=2.3.0; extra == 'dlesym'
Requires-Dist: pytz; extra == 'dlesym'
Provides-Extra: dlwp
Requires-Dist: importlib-metadata; extra == 'dlwp'
Requires-Dist: nvidia-physicsnemo<2.0,>=1.0.1; extra == 'dlwp'
Requires-Dist: pytz; extra == 'dlwp'
Provides-Extra: fcn
Requires-Dist: nvidia-physicsnemo<2.0,>=1.0.1; extra == 'fcn'
Requires-Dist: pytz; extra == 'fcn'
Provides-Extra: fcn3
Requires-Dist: makani; extra == 'fcn3'
Requires-Dist: moviepy; extra == 'fcn3'
Requires-Dist: pytz; extra == 'fcn3'
Requires-Dist: ruamel-yaml>=0.18.14; extra == 'fcn3'
Requires-Dist: scipy>=1.10.0; extra == 'fcn3'
Requires-Dist: torch-harmonics>=0.8.0; extra == 'fcn3'
Provides-Extra: fengwu
Requires-Dist: onnx; extra == 'fengwu'
Requires-Dist: onnxruntime-gpu>=1.21.0; extra == 'fengwu'
Requires-Dist: onnxscript; extra == 'fengwu'
Provides-Extra: fuxi
Requires-Dist: onnx; extra == 'fuxi'
Requires-Dist: onnxruntime-gpu>=1.21.0; extra == 'fuxi'
Requires-Dist: onnxscript; extra == 'fuxi'
Provides-Extra: graphcast
Requires-Dist: dm-haiku>=0.0.14; extra == 'graphcast'
Requires-Dist: dm-tree>=0.1.9; extra == 'graphcast'
Requires-Dist: flax>=0.10.6; extra == 'graphcast'
Requires-Dist: graphcast; extra == 'graphcast'
Requires-Dist: jax[cuda12]>=0.4.26; extra == 'graphcast'
Provides-Extra: interp-modafno
Requires-Dist: nvidia-physicsnemo<2.0,>=1.0.1; extra == 'interp-modafno'
Requires-Dist: pytz; extra == 'interp-modafno'
Provides-Extra: pangu
Requires-Dist: onnx; extra == 'pangu'
Requires-Dist: onnxruntime-gpu>=1.21.0; extra == 'pangu'
Requires-Dist: onnxscript; extra == 'pangu'
Provides-Extra: perturbation
Requires-Dist: scipy>=1.15.2; extra == 'perturbation'
Requires-Dist: torch-harmonics>=0.7.4; extra == 'perturbation'
Provides-Extra: precip-afno
Requires-Dist: nvidia-physicsnemo<2.0,>=1.0.1; extra == 'precip-afno'
Requires-Dist: pytz; extra == 'precip-afno'
Provides-Extra: precip-afno-v2
Requires-Dist: nvidia-physicsnemo<2.0,>=1.0.1; extra == 'precip-afno-v2'
Requires-Dist: pytz; extra == 'precip-afno-v2'
Provides-Extra: sfno
Requires-Dist: makani; extra == 'sfno'
Requires-Dist: moviepy; extra == 'sfno'
Requires-Dist: pynvml>=12.0.0; extra == 'sfno'
Requires-Dist: ruamel-yaml>=0.18.10; extra == 'sfno'
Requires-Dist: scipy>=1.10.0; extra == 'sfno'
Requires-Dist: torch-harmonics>=0.8.0; extra == 'sfno'
Provides-Extra: solarradiation-afno
Requires-Dist: nvidia-physicsnemo<2.0,>=1.0.1; extra == 'solarradiation-afno'
Requires-Dist: pytz; extra == 'solarradiation-afno'
Provides-Extra: statistics
Requires-Dist: nvidia-physicsnemo<2.0,>=1.0.1; extra == 'statistics'
Requires-Dist: pytz; extra == 'statistics'
Provides-Extra: stormcast
Requires-Dist: einops>=0.8.1; extra == 'stormcast'
Requires-Dist: nvidia-physicsnemo<2.0,>=1.0.1; extra == 'stormcast'
Requires-Dist: nvtx>=0.2.11; extra == 'stormcast'
Requires-Dist: omegaconf>=2.3.0; extra == 'stormcast'
Requires-Dist: pyproj>=3.7.1; extra == 'stormcast'
Requires-Dist: pytz; extra == 'stormcast'
Requires-Dist: scipy>=1.15.2; extra == 'stormcast'
Provides-Extra: stormscope
Requires-Dist: earth2grid; extra == 'stormscope'
Requires-Dist: natten; extra == 'stormscope'
Requires-Dist: nvidia-physicsnemo==1.3.0; extra == 'stormscope'
Requires-Dist: nvtx>=0.2.11; extra == 'stormscope'
Requires-Dist: pytz; extra == 'stormscope'
Requires-Dist: scipy>=1.15.2; extra == 'stormscope'
Provides-Extra: utils
Requires-Dist: earth2grid; extra == 'utils'
Requires-Dist: scipy>=1.15.2; extra == 'utils'
Provides-Extra: windgust-afno
Requires-Dist: nvidia-physicsnemo<2.0,>=1.0.1; extra == 'windgust-afno'
Requires-Dist: pytz; extra == 'windgust-afno'
